pyevaljs4/__init__.py
pyevaljs4/__version__.py
pyevaljs4/_program.py
pyevaljs4/exceptions.py
pyevaljs4/pyevaljs.py
pyevaljs4/settings.py
pyevaljs4/utils.py
pyevaljs4-0.2.0.dist-info/METADATA
pyevaljs4-0.2.0.dist-info/WHEEL
pyevaljs4-0.2.0.dist-info/top_level.txt
pyevaljs4-0.2.0.dist-info/RECORD
