Metadata-Version: 2.1
Name: pyevaljs4
Version: 0.2.0
Summary: A high-performance Python library that relies on nodejs to execute JavaScript
Home-page: https://github.com/Smawexi/PyEvalJS4
Author: Samwe
Author-email: 1281722462@qq.com
Classifier: Programming Language :: Python :: 3.7
Classifier: Programming Language :: Python :: 3.8
Classifier: Programming Language :: Python :: 3.9
Classifier: Programming Language :: Python :: 3.10
Classifier: Programming Language :: Python :: 3.11
Classifier: Programming Language :: Python :: 3.12
Classifier: Programming Language :: Python :: 3.13
Classifier: Programming Language :: Python :: Implementation :: CPython
Classifier: License :: OSI Approved :: MIT License
Requires-Python: >=3.7.0
